package/__init__.py
package/__main__.py
package/marcownpack.py
marcownpack-1.2.1.dist-info/LICENSE
marcownpack-1.2.1.dist-info/METADATA
marcownpack-1.2.1.dist-info/WHEEL
marcownpack-1.2.1.dist-info/entry_points.txt
marcownpack-1.2.1.dist-info/top_level.txt
marcownpack-1.2.1.dist-info/RECORD
