Metadata-Version: 2.1
Name: marcownpack
Version: 1.2.1
Summary: oh hi lolz
Home-page: https://github.com/imadethisaccountsoicanmakeanissue/marcownpack
Author: Marc Thompson
Author-email: taoun11ttu@outlook.com
License: BSD-2-Clause
Project-URL: Documentation, https://github.com/imadethisaccountsoicanmakeanissue/marcownpack/wiki
Keywords: my,package,keywords
Platform: UNKNOWN
Classifier: Development Status :: 5 - Production/Stable
Classifier: License :: OSI Approved :: BSD License
Classifier: Operating System :: OS Independent
Classifier: Programming Language :: Python
Classifier: Programming Language :: Python :: 3
Requires-Python: >=3.6
Requires-Dist: setuptools
Requires-Dist: wheel
Provides-Extra: docs
Requires-Dist: sphinx ; extra == 'docs'
Requires-Dist: sphinx-rtd-theme ; extra == 'docs'
